vardiff/__init__.py
vardiff/comparator.py
vardiff/file_comparator.py
vardiff-0.2.6.dist-info/licenses/LICENSE.txt
vardiff-0.2.6.dist-info/METADATA
vardiff-0.2.6.dist-info/WHEEL
vardiff-0.2.6.dist-info/top_level.txt
vardiff-0.2.6.dist-info/RECORD
